quantling/__init__.py
quantling/depval.py
quantling/lawfitter.py
quantling/lingnet.py
quantling-0.1.1.dist-info/LICENSE
quantling-0.1.1.dist-info/METADATA
quantling-0.1.1.dist-info/WHEEL
quantling-0.1.1.dist-info/top_level.txt
quantling-0.1.1.dist-info/RECORD
