Metadata-Version: 2.1
Name: quantling
Version: 0.1.1
Summary: A package for quantiative linguistics
Home-page: https://github.com/YuhuYang/QuantLing
Author: Mu Yang
Author-email: yuhuyang@163.com
Classifier: Programming Language :: Python :: 3
Classifier: License :: OSI Approved :: MIT License
Classifier: Operating System :: OS Independent
Requires-Python: >=3.6
License-File: LICENSE
